nxtools/__init__.py
nxtools/caspar/__init__.py
nxtools/caspar/caspar.py
nxtools/common.py
nxtools/files.py
nxtools/logging.py
nxtools/media/__init__.py
nxtools/media/ffanalyse.py
nxtools/media/fffilters.py
nxtools/media/ffmpeg.py
nxtools/media/ffprobe.py
nxtools/text.py
nxtools/timeutils.py
nxtools/version.py
nxtools-1.6.dist-info/entry_points.txt
nxtools-1.6.dist-info/LICENSE
nxtools-1.6.dist-info/WHEEL
nxtools-1.6.dist-info/METADATA
nxtools-1.6.dist-info/RECORD
