Metadata-Version: 2.1
Name: nxtools
Version: 1.6
Summary: nxtools is a set of various tools and helpers used by Nebula broadcast automation system and other software by imm studios, z.s.
Home-page: https://github.com/immstudios/nxtools
License: MIT
Keywords: utilities,logging,automation,ffmpeg,casparcg
Author: Martin Wacker
Author-email: martas@imm.cz
Requires-Python: >=3.6,<4.0
Classifier: Development Status :: 5 - Production/Stable
Classifier: Environment :: Console
Classifier: Intended Audience :: Developers
Classifier: License :: OSI Approved :: MIT License
Classifier: Natural Language :: English
Classifier: Operating System :: POSIX :: Linux
Classifier: Programming Language :: Python
Classifier: Programming Language :: Python :: 3
Classifier: Programming Language :: Python :: 3.6
Classifier: Programming Language :: Python :: 3.7
Classifier: Programming Language :: Python :: 3.8
Classifier: Programming Language :: Python :: 3.9
Classifier: Topic :: Multimedia :: Video :: Conversion
Classifier: Topic :: Utilities
Requires-Dist: Unidecode (>=1.2.0,<2.0.0)
Requires-Dist: colorama (>=0.4.4,<0.5.0)
Project-URL: Repository, https://github.com/immstudios/nxtools
